setup.py
distributions/Binomialdistribution.py
distributions/Gaussiandistribution.py
distributions/Generaldistribution.py
distributions/__init__.py
macieju7777_distributions.egg-info/PKG-INFO
macieju7777_distributions.egg-info/SOURCES.txt
macieju7777_distributions.egg-info/dependency_links.txt
macieju7777_distributions.egg-info/not-zip-safe
macieju7777_distributions.egg-info/top_level.txt